minidns
