Metadata-Version: 1.1
Name: minidns
Version: 0.2
Summary: Simple DNS Server with REST API, for localhost only
Home-page: http://github.com/yaybu/minidns
Author: Doug Winter
Author-email: doug.winter@isotoma.com
License: Apache Software License
Platform: UNKNOWN
Classifier: Development Status :: 4 - Beta
Classifier: Environment :: Console
Classifier: Framework :: Twisted
Classifier: Intended Audience :: Developers
Classifier: License :: OSI Approved :: Apache Software License
Classifier: Topic :: Internet :: Name Service (DNS)
